MANIFEST.in
README.md
requirements.txt
setup.py
version.py
bdgenomics/__init__.py
bdgenomics.mango.egg-info/PKG-INFO
bdgenomics.mango.egg-info/SOURCES.txt
bdgenomics.mango.egg-info/dependency_links.txt
bdgenomics.mango.egg-info/requires.txt
bdgenomics.mango.egg-info/top_level.txt
bdgenomics/mango/__init__.py
bdgenomics/mango/alignments.py
bdgenomics/mango/coverage.py
bdgenomics/mango/distribution.py
bdgenomics/mango/features.py
bdgenomics/mango/genotypes.py
bdgenomics/mango/utils.py
bdgenomics/mango/variants.py
bdgenomics/mango/test/__init__.py
bdgenomics/mango/test/alignment_test.py
bdgenomics/mango/test/coverage_test.py
bdgenomics/mango/test/distribution_test.py
bdgenomics/mango/test/feature_test.py
bdgenomics/mango/test/genotypes_test.py
bdgenomics/mango/test/notebook_test.py
bdgenomics/mango/test/variant_test.py