Metadata-Version: 1.0
Name: bdgenomics.mango
Version: 0.0.2a1
Summary: A scalable genomic visualization tool
Home-page: https://github.com/bdgenomics/mango
Author: Alyssa Morrow
Author-email: akmorrow@berkeley.edu
License: UNKNOWN
Platform: UNKNOWN
